pil_font_maker/__init__.py
pil_font_maker/pil_font_maker.py
pil_font_maker-0.9.7.dist-info/LICENSE
pil_font_maker-0.9.7.dist-info/METADATA
pil_font_maker-0.9.7.dist-info/WHEEL
pil_font_maker-0.9.7.dist-info/entry_points.txt
pil_font_maker-0.9.7.dist-info/top_level.txt
pil_font_maker-0.9.7.dist-info/RECORD
