Metadata-Version: 2.1
Name: pil-font-maker
Version: 0.9.7
Summary: A tool to make a PILfont from png images
Home-page: https://github.com/haarsmam/pil-font-maker
Author: Marc Haarsma
Author-email: marc.haarsma@gmail.com
License-File: LICENSE
Requires-Dist: Pillow
